pymongo_mate/__init__.py
pymongo_mate/__init__.pyc
pymongo_mate/mongomock_mate.py
pymongo_mate/mongomock_mate.pyc
pymongo_mate/query_builder.py
pymongo_mate/query_builder.pyc
pymongo_mate/utils.py
pymongo_mate/utils.pyc
pymongo_mate/crud/__init__.py
pymongo_mate/crud/__init__.pyc
pymongo_mate/crud/insert.py
pymongo_mate/crud/insert.pyc
pymongo_mate/crud/select.py
pymongo_mate/crud/select.pyc
pymongo_mate/crud/update.py
pymongo_mate/crud/update.pyc
pymongo_mate/pkg/__init__.py
pymongo_mate/pkg/__init__.pyc
pymongo_mate/pkg/sixmini.py
pymongo_mate/pkg/sixmini.pyc
pymongo_mate/pkg/pandas_mate/__init__.py
pymongo_mate/pkg/pandas_mate/__init__.pyc
pymongo_mate/pkg/pandas_mate/csv_io.py
pymongo_mate/pkg/pandas_mate/sql_io.py
pymongo_mate/pkg/pandas_mate/transform.py
pymongo_mate/pkg/pandas_mate/transform.pyc
pymongo_mate/pkg/pandas_mate/util.py
pymongo_mate/pkg/pandas_mate/zzz_manual_install.py
pymongo_mate/pkg/pandas_mate/pkg/__init__.py
pymongo_mate/pkg/pandas_mate/pkg/__init__.pyc
pymongo_mate/pkg/pandas_mate/pkg/prettytable/__init__.py
pymongo_mate/pkg/pandas_mate/pkg/prettytable/_compact.py
pymongo_mate/pkg/pandas_mate/pkg/prettytable/cli.py
pymongo_mate/pkg/pandas_mate/pkg/prettytable/factory.py
pymongo_mate/pkg/pandas_mate/pkg/prettytable/prettytable.py
pymongo_mate/pkg/pandas_mate/pkg/rolex/__init__.py
pymongo_mate/pkg/pandas_mate/pkg/rolex/__init__.pyc
pymongo_mate/pkg/pandas_mate/pkg/rolex/six.py
pymongo_mate/pkg/pandas_mate/pkg/rolex/six.pyc
pymongo_mate/pkg/pandas_mate/pkg/rolex/template.py
pymongo_mate/pkg/pandas_mate/pkg/rolex/template.pyc
pymongo_mate/pkg/pandas_mate/pkg/rolex/zzz_manual_install.py
pymongo_mate/pkg/pandas_mate/tests/__init__.py
pymongo_mate/tests/__init__.py
pymongo_mate/tests/__init__.pyc
pymongo_mate-0.0.4.dist-info/DESCRIPTION.rst
pymongo_mate-0.0.4.dist-info/METADATA
pymongo_mate-0.0.4.dist-info/RECORD
pymongo_mate-0.0.4.dist-info/WHEEL
pymongo_mate-0.0.4.dist-info/metadata.json
pymongo_mate-0.0.4.dist-info/top_level.txt
